inekf-0.1.0.dist-info/RECORD
inekf-0.1.0.dist-info/WHEEL
inekf-0.1.0.dist-info/METADATA
inekf-0.1.0.dist-info/top_level.txt
inekf/__init__.py
inekf/_inekf.cpython-38-x86_64-linux-gnu.so
inekf/lie_groups.py
inekf/_docs.py
inekf/base.py
