Metadata-Version: 2.1
Name: inekf
Version: 0.1.0
Summary: BYU Invariant Extended Kalman Filter Library
Home-page: https://bitbucket.org/frostlab/inekf/
Author: Easton Potokar
Author-email: eastonpots@byu.edu
License: MIT License
Keywords: invariant kalman filter robotics localization
Platform: UNKNOWN
Classifier: Development Status :: 4 - Beta
Classifier: Intended Audience :: Education
Classifier: Intended Audience :: Developers
Classifier: Intended Audience :: Science/Research
Classifier: Operating System :: POSIX
Classifier: Programming Language :: Python :: 3
Classifier: Programming Language :: Python :: 3.7
Classifier: Programming Language :: Python :: 3.8
Classifier: Programming Language :: Python :: 3.9
Classifier: Programming Language :: Python :: 3.10
Requires-Dist: numpy
